[{"porto":"Itaja\u00ed","CO_CUCI_GRUPO":"011","NO_CUCI_GRUPO":"Carne bovina fresca, refrigerada ou congelada","VL_FOB":3596671680,"hhi_pauta":0.1133349936,"hhi_portuario":0.4572716217},{"porto":"Paranagu\u00e1","CO_CUCI_GRUPO":"011","NO_CUCI_GRUPO":"Carne bovina fresca, refrigerada ou congelada","VL_FOB":16221365643,"hhi_pauta":0.1125121844,"hhi_portuario":0.4572716217},{"porto":"Santos","CO_CUCI_GRUPO":"011","NO_CUCI_GRUPO":"Carne bovina fresca, refrigerada ou congelada","VL_FOB":58957159523,"hhi_pauta":0.0500308157,"hhi_portuario":0.4572716217},{"porto":"S\u00e3o Francisco do Sul","CO_CUCI_GRUPO":"011","NO_CUCI_GRUPO":"Carne bovina fresca, refrigerada ou congelada","VL_FOB":7809287575,"hhi_pauta":0.1115259415,"hhi_portuario":0.4572716217},{"porto":"Vila do Conde","CO_CUCI_GRUPO":"011","NO_CUCI_GRUPO":"Carne bovina fresca, refrigerada ou congelada","VL_FOB":2761360307,"hhi_pauta":0.1989042511,"hhi_portuario":0.4572716217},{"porto":"Itaja\u00ed","CO_CUCI_GRUPO":"012c1","NO_CUCI_GRUPO":"Carnes de aves e suas miudezas comest\u00edveis, frescas, refrigeradas ou congeladas","VL_FOB":24372276961,"hhi_pauta":0.1133349936,"hhi_portuario":0.27756361},{"porto":"Paranagu\u00e1","CO_CUCI_GRUPO":"012c1","NO_CUCI_GRUPO":"Carnes de aves e suas miudezas comest\u00edveis, frescas, refrigeradas ou congeladas","VL_FOB":35152985194,"hhi_pauta":0.1125121844,"hhi_portuario":0.27756361},{"porto":"Rio Grande","CO_CUCI_GRUPO":"012c1","NO_CUCI_GRUPO":"Carnes de aves e suas miudezas comest\u00edveis, frescas, refrigeradas ou congeladas","VL_FOB":5773814080,"hhi_pauta":0.132143181,"hhi_portuario":0.27756361},{"porto":"Santos","CO_CUCI_GRUPO":"012c1","NO_CUCI_GRUPO":"Carnes de aves e suas miudezas comest\u00edveis, frescas, refrigeradas ou congeladas","VL_FOB":8486012101,"hhi_pauta":0.0500308157,"hhi_portuario":0.27756361},{"porto":"S\u00e3o Francisco do Sul","CO_CUCI_GRUPO":"012c1","NO_CUCI_GRUPO":"Carnes de aves e suas miudezas comest\u00edveis, frescas, refrigeradas ou congeladas","VL_FOB":10784156225,"hhi_pauta":0.1115259415,"hhi_portuario":0.27756361},{"porto":"Manaus","CO_CUCI_GRUPO":"044","NO_CUCI_GRUPO":"Milho n\u00e3o mo\u00eddo, exceto milho doce","VL_FOB":3367533332,"hhi_pauta":0.3820246506,"hhi_portuario":0.265838669},{"porto":"Paranagu\u00e1","CO_CUCI_GRUPO":"044","NO_CUCI_GRUPO":"Milho n\u00e3o mo\u00eddo, exceto milho doce","VL_FOB":8521314201,"hhi_pauta":0.1125121844,"hhi_portuario":0.265838669},{"porto":"Santos","CO_CUCI_GRUPO":"044","NO_CUCI_GRUPO":"Milho n\u00e3o mo\u00eddo, exceto milho doce","VL_FOB":33851466464,"hhi_pauta":0.0500308157,"hhi_portuario":0.265838669},{"porto":"S\u00e3o Francisco do Sul","CO_CUCI_GRUPO":"044","NO_CUCI_GRUPO":"Milho n\u00e3o mo\u00eddo, exceto milho doce","VL_FOB":4516375146,"hhi_pauta":0.1115259415,"hhi_portuario":0.265838669},{"porto":"S\u00e3o Lu\u00eds","CO_CUCI_GRUPO":"044","NO_CUCI_GRUPO":"Milho n\u00e3o mo\u00eddo, exceto milho doce","VL_FOB":7727574194,"hhi_pauta":0.3603558587,"hhi_portuario":0.265838669},{"porto":"Vila do Conde","CO_CUCI_GRUPO":"044","NO_CUCI_GRUPO":"Milho n\u00e3o mo\u00eddo, exceto milho doce","VL_FOB":11368235386,"hhi_pauta":0.1989042511,"hhi_portuario":0.265838669},{"porto":"Vit\u00f3ria","CO_CUCI_GRUPO":"044","NO_CUCI_GRUPO":"Milho n\u00e3o mo\u00eddo, exceto milho doce","VL_FOB":2581089167,"hhi_pauta":0.2255800281,"hhi_portuario":0.265838669},{"porto":"Santos","CO_CUCI_GRUPO":"059","NO_CUCI_GRUPO":"Sucos de frutas ou de vegetais","VL_FOB":25514743860,"hhi_pauta":0.0500308157,"hhi_portuario":0.835385241},{"porto":"Paranagu\u00e1","CO_CUCI_GRUPO":"061c","NO_CUCI_GRUPO":"A\u00e7\u00facares e mela\u00e7os","VL_FOB":23650729926,"hhi_pauta":0.1125121844,"hhi_portuario":0.6575639515},{"porto":"Santos","CO_CUCI_GRUPO":"061c","NO_CUCI_GRUPO":"A\u00e7\u00facares e mela\u00e7os","VL_FOB":94002912774,"hhi_pauta":0.0500308157,"hhi_portuario":0.6575639515},{"porto":"Rio de Janeiro","CO_CUCI_GRUPO":"071a","NO_CUCI_GRUPO":"Caf\u00e9 n\u00e3o torrado","VL_FOB":11449783059,"hhi_pauta":0.0832038951,"hhi_portuario":0.6834103541},{"porto":"Santos","CO_CUCI_GRUPO":"071a","NO_CUCI_GRUPO":"Caf\u00e9 n\u00e3o torrado","VL_FOB":67229766165,"hhi_pauta":0.0500308157,"hhi_portuario":0.6834103541},{"porto":"Paranagu\u00e1","CO_CUCI_GRUPO":"081c","NO_CUCI_GRUPO":"Farelos de soja e outros alimentos para animais (exclu\u00eddos cereais n\u00e3o mo\u00eddos), farinhas de carnes e outros animais","VL_FOB":26785616356,"hhi_pauta":0.1125121844,"hhi_portuario":0.2923886532},{"porto":"Rio Grande","CO_CUCI_GRUPO":"081c","NO_CUCI_GRUPO":"Farelos de soja e outros alimentos para animais (exclu\u00eddos cereais n\u00e3o mo\u00eddos), farinhas de carnes e outros animais","VL_FOB":13850185225,"hhi_pauta":0.132143181,"hhi_portuario":0.2923886532},{"porto":"Salvador","CO_CUCI_GRUPO":"081c","NO_CUCI_GRUPO":"Farelos de soja e outros alimentos para animais (exclu\u00eddos cereais n\u00e3o mo\u00eddos), farinhas de carnes e outros animais","VL_FOB":4285567459,"hhi_pauta":0.1365252407,"hhi_portuario":0.2923886532},{"porto":"Santos","CO_CUCI_GRUPO":"081c","NO_CUCI_GRUPO":"Farelos de soja e outros alimentos para animais (exclu\u00eddos cereais n\u00e3o mo\u00eddos), farinhas de carnes e outros animais","VL_FOB":37563699989,"hhi_pauta":0.0500308157,"hhi_portuario":0.2923886532},{"porto":"Itaja\u00ed","CO_CUCI_GRUPO":"121c","NO_CUCI_GRUPO":"Tabaco, descaulificado ou desnervado","VL_FOB":3966180210,"hhi_pauta":0.1133349936,"hhi_portuario":0.6969084772},{"porto":"Rio Grande","CO_CUCI_GRUPO":"121c","NO_CUCI_GRUPO":"Tabaco, descaulificado ou desnervado","VL_FOB":20008600297,"hhi_pauta":0.132143181,"hhi_portuario":0.6969084772},{"porto":"Manaus","CO_CUCI_GRUPO":"222a1","NO_CUCI_GRUPO":"Soja","VL_FOB":15632264784,"hhi_pauta":0.3820246506,"hhi_portuario":0.1633583979},{"porto":"Paranagu\u00e1","CO_CUCI_GRUPO":"222a1","NO_CUCI_GRUPO":"Soja","VL_FOB":60829618632,"hhi_pauta":0.1125121844,"hhi_portuario":0.1633583979},{"porto":"Rio Grande","CO_CUCI_GRUPO":"222a1","NO_CUCI_GRUPO":"Soja","VL_FOB":54119067932,"hhi_pauta":0.132143181,"hhi_portuario":0.1633583979},{"porto":"Salvador","CO_CUCI_GRUPO":"222a1","NO_CUCI_GRUPO":"Soja","VL_FOB":13197538881,"hhi_pauta":0.1365252407,"hhi_portuario":0.1633583979},{"porto":"Santos","CO_CUCI_GRUPO":"222a1","NO_CUCI_GRUPO":"Soja","VL_FOB":111672001395,"hhi_pauta":0.0500308157,"hhi_portuario":0.1633583979},{"porto":"S\u00e3o Francisco do Sul","CO_CUCI_GRUPO":"222a1","NO_CUCI_GRUPO":"Soja","VL_FOB":25652869335,"hhi_pauta":0.1115259415,"hhi_portuario":0.1633583979},{"porto":"S\u00e3o Lu\u00eds","CO_CUCI_GRUPO":"222a1","NO_CUCI_GRUPO":"Soja","VL_FOB":46616647203,"hhi_pauta":0.3603558587,"hhi_portuario":0.1633583979},{"porto":"Vila do Conde","CO_CUCI_GRUPO":"222a1","NO_CUCI_GRUPO":"Soja","VL_FOB":32153818034,"hhi_pauta":0.1989042511,"hhi_portuario":0.1633583979},{"porto":"Vit\u00f3ria","CO_CUCI_GRUPO":"222a1","NO_CUCI_GRUPO":"Soja","VL_FOB":20063593305,"hhi_pauta":0.2255800281,"hhi_portuario":0.1633583979},{"porto":"Paranagu\u00e1","CO_CUCI_GRUPO":"251c","NO_CUCI_GRUPO":"Celulose","VL_FOB":5801409926,"hhi_pauta":0.1125121844,"hhi_portuario":0.2586905342},{"porto":"Rio Grande","CO_CUCI_GRUPO":"251c","NO_CUCI_GRUPO":"Celulose","VL_FOB":8914731952,"hhi_pauta":0.132143181,"hhi_portuario":0.2586905342},{"porto":"Santos","CO_CUCI_GRUPO":"251c","NO_CUCI_GRUPO":"Celulose","VL_FOB":28220955774,"hhi_pauta":0.0500308157,"hhi_portuario":0.2586905342},{"porto":"S\u00e3o Lu\u00eds","CO_CUCI_GRUPO":"251c","NO_CUCI_GRUPO":"Celulose","VL_FOB":8170996161,"hhi_pauta":0.3603558587,"hhi_portuario":0.2586905342},{"porto":"Vit\u00f3ria","CO_CUCI_GRUPO":"251c","NO_CUCI_GRUPO":"Celulose","VL_FOB":30898677923,"hhi_pauta":0.2255800281,"hhi_portuario":0.2586905342},{"porto":"Santos","CO_CUCI_GRUPO":"263a","NO_CUCI_GRUPO":"Algod\u00e3o em bruto","VL_FOB":32014685320,"hhi_pauta":0.0500308157,"hhi_portuario":0.9172701546},{"porto":"Itagua\u00ed","CO_CUCI_GRUPO":"281b","NO_CUCI_GRUPO":"Min\u00e9rio de ferro e seus concentrados","VL_FOB":69941224842,"hhi_pauta":0.3485001434,"hhi_portuario":0.3236813595},{"porto":"S\u00e3o Jo\u00e3o da Barra","CO_CUCI_GRUPO":"281b","NO_CUCI_GRUPO":"Min\u00e9rio de ferro e seus concentrados","VL_FOB":17817174316,"hhi_pauta":0.6437140645,"hhi_portuario":0.3236813595},{"porto":"S\u00e3o Lu\u00eds","CO_CUCI_GRUPO":"281b","NO_CUCI_GRUPO":"Min\u00e9rio de ferro e seus concentrados","VL_FOB":134010859814,"hhi_pauta":0.3603558587,"hhi_portuario":0.3236813595},{"porto":"Vit\u00f3ria","CO_CUCI_GRUPO":"281b","NO_CUCI_GRUPO":"Min\u00e9rio de ferro e seus concentrados","VL_FOB":80560805404,"hhi_pauta":0.2255800281,"hhi_portuario":0.3236813595},{"porto":"S\u00e3o Lu\u00eds","CO_CUCI_GRUPO":"283b","NO_CUCI_GRUPO":"Min\u00e9rios de cobre e seus concentrados","VL_FOB":25763191031,"hhi_pauta":0.3603558587,"hhi_portuario":0.6539311712},{"porto":"Vit\u00f3ria","CO_CUCI_GRUPO":"283b","NO_CUCI_GRUPO":"Min\u00e9rios de cobre e seus concentrados","VL_FOB":3360361683,"hhi_pauta":0.2255800281,"hhi_portuario":0.6539311712},{"porto":"S\u00e3o Lu\u00eds","CO_CUCI_GRUPO":"285c","NO_CUCI_GRUPO":"Alumina (\u00f3xido de alum\u00ednio), exceto corindo artificial","VL_FOB":14622661164,"hhi_pauta":0.3603558587,"hhi_portuario":0.4984568692},{"porto":"Vila do Conde","CO_CUCI_GRUPO":"285c","NO_CUCI_GRUPO":"Alumina (\u00f3xido de alum\u00ednio), exceto corindo artificial","VL_FOB":17574502884,"hhi_pauta":0.1989042511,"hhi_portuario":0.4984568692},{"porto":"Itagua\u00ed","CO_CUCI_GRUPO":"333","NO_CUCI_GRUPO":"\u00d3leos brutos de petr\u00f3leo ou de minerais betuminosos, crus","VL_FOB":117893711889,"hhi_pauta":0.3485001434,"hhi_portuario":0.3415353132},{"porto":"Santos","CO_CUCI_GRUPO":"333","NO_CUCI_GRUPO":"\u00d3leos brutos de petr\u00f3leo ou de minerais betuminosos, crus","VL_FOB":48408249554,"hhi_pauta":0.0500308157,"hhi_portuario":0.3415353132},{"porto":"S\u00e3o Jo\u00e3o da Barra","CO_CUCI_GRUPO":"333","NO_CUCI_GRUPO":"\u00d3leos brutos de petr\u00f3leo ou de minerais betuminosos, crus","VL_FOB":73025827827,"hhi_pauta":0.6437140645,"hhi_portuario":0.3415353132},{"porto":"Vit\u00f3ria","CO_CUCI_GRUPO":"333","NO_CUCI_GRUPO":"\u00d3leos brutos de petr\u00f3leo ou de minerais betuminosos, crus","VL_FOB":11048868196,"hhi_pauta":0.2255800281,"hhi_portuario":0.3415353132},{"porto":"Itagua\u00ed","CO_CUCI_GRUPO":"334c","NO_CUCI_GRUPO":"\u00d3leos combust\u00edveis de petr\u00f3leo ou de minerais betuminosos (exceto \u00f3leos brutos)","VL_FOB":4443213322,"hhi_pauta":0.3485001434,"hhi_portuario":0.1847268749},{"porto":"Rio de Janeiro","CO_CUCI_GRUPO":"334c","NO_CUCI_GRUPO":"\u00d3leos combust\u00edveis de petr\u00f3leo ou de minerais betuminosos (exceto \u00f3leos brutos)","VL_FOB":12000336189,"hhi_pauta":0.0832038951,"hhi_portuario":0.1847268749},{"porto":"Salvador","CO_CUCI_GRUPO":"334c","NO_CUCI_GRUPO":"\u00d3leos combust\u00edveis de petr\u00f3leo ou de minerais betuminosos (exceto \u00f3leos brutos)","VL_FOB":14112274278,"hhi_pauta":0.1365252407,"hhi_portuario":0.1847268749},{"porto":"Santos","CO_CUCI_GRUPO":"334c","NO_CUCI_GRUPO":"\u00d3leos combust\u00edveis de petr\u00f3leo ou de minerais betuminosos (exceto \u00f3leos brutos)","VL_FOB":10924971478,"hhi_pauta":0.0500308157,"hhi_portuario":0.1847268749},{"porto":"Suape","CO_CUCI_GRUPO":"334c","NO_CUCI_GRUPO":"\u00d3leos combust\u00edveis de petr\u00f3leo ou de minerais betuminosos (exceto \u00f3leos brutos)","VL_FOB":7241571697,"hhi_pauta":0.2002748856,"hhi_portuario":0.1847268749},{"porto":"Itagua\u00ed","CO_CUCI_GRUPO":"671","NO_CUCI_GRUPO":"Ferro-gusa, spiegel, ferro-esponja, gr\u00e2nulos e p\u00f3 de ferro ou a\u00e7o e ferro-ligas","VL_FOB":3448470033,"hhi_pauta":0.3485001434,"hhi_portuario":0.2734124046},{"porto":"Rio de Janeiro","CO_CUCI_GRUPO":"671","NO_CUCI_GRUPO":"Ferro-gusa, spiegel, ferro-esponja, gr\u00e2nulos e p\u00f3 de ferro ou a\u00e7o e ferro-ligas","VL_FOB":11984079146,"hhi_pauta":0.0832038951,"hhi_portuario":0.2734124046},{"porto":"Santos","CO_CUCI_GRUPO":"671","NO_CUCI_GRUPO":"Ferro-gusa, spiegel, ferro-esponja, gr\u00e2nulos e p\u00f3 de ferro ou a\u00e7o e ferro-ligas","VL_FOB":23414344636,"hhi_pauta":0.0500308157,"hhi_portuario":0.2734124046},{"porto":"S\u00e3o Lu\u00eds","CO_CUCI_GRUPO":"671","NO_CUCI_GRUPO":"Ferro-gusa, spiegel, ferro-esponja, gr\u00e2nulos e p\u00f3 de ferro ou a\u00e7o e ferro-ligas","VL_FOB":3214183722,"hhi_pauta":0.3603558587,"hhi_portuario":0.2734124046},{"porto":"Vila do Conde","CO_CUCI_GRUPO":"671","NO_CUCI_GRUPO":"Ferro-gusa, spiegel, ferro-esponja, gr\u00e2nulos e p\u00f3 de ferro ou a\u00e7o e ferro-ligas","VL_FOB":2881429584,"hhi_pauta":0.1989042511,"hhi_portuario":0.2734124046},{"porto":"Vit\u00f3ria","CO_CUCI_GRUPO":"671","NO_CUCI_GRUPO":"Ferro-gusa, spiegel, ferro-esponja, gr\u00e2nulos e p\u00f3 de ferro ou a\u00e7o e ferro-ligas","VL_FOB":4950294642,"hhi_pauta":0.2255800281,"hhi_portuario":0.2734124046},{"porto":"Itagua\u00ed","CO_CUCI_GRUPO":"672","NO_CUCI_GRUPO":"Produtos semi-acabados, lingotes e outras formas prim\u00e1rias de ferro ou a\u00e7o","VL_FOB":23816216890,"hhi_pauta":0.3485001434,"hhi_portuario":0.3568299361},{"porto":"Pec\u00e9m","CO_CUCI_GRUPO":"672","NO_CUCI_GRUPO":"Produtos semi-acabados, lingotes e outras formas prim\u00e1rias de ferro ou a\u00e7o","VL_FOB":10019028530,"hhi_pauta":0.2491545866,"hhi_portuario":0.3568299361},{"porto":"Vit\u00f3ria","CO_CUCI_GRUPO":"672","NO_CUCI_GRUPO":"Produtos semi-acabados, lingotes e outras formas prim\u00e1rias de ferro ou a\u00e7o","VL_FOB":19442191333,"hhi_pauta":0.2255800281,"hhi_portuario":0.3568299361},{"porto":"Santos","CO_CUCI_GRUPO":"723","NO_CUCI_GRUPO":"Instala\u00e7\u00f5es e equipamentos de engenharia civil e contrutores, e suas partes","VL_FOB":23570144432,"hhi_pauta":0.0500308157,"hhi_portuario":0.8179457759},{"porto":"Paranagu\u00e1","CO_CUCI_GRUPO":"781","NO_CUCI_GRUPO":"Ve\u00edculos autom\u00f3veis de passageiros","VL_FOB":6875075412,"hhi_pauta":0.1125121844,"hhi_portuario":0.3386946798},{"porto":"Rio de Janeiro","CO_CUCI_GRUPO":"781","NO_CUCI_GRUPO":"Ve\u00edculos autom\u00f3veis de passageiros","VL_FOB":4190264598,"hhi_pauta":0.0832038951,"hhi_portuario":0.3386946798},{"porto":"Santos","CO_CUCI_GRUPO":"781","NO_CUCI_GRUPO":"Ve\u00edculos autom\u00f3veis de passageiros","VL_FOB":19315129153,"hhi_pauta":0.0500308157,"hhi_portuario":0.3386946798},{"porto":"Suape","CO_CUCI_GRUPO":"781","NO_CUCI_GRUPO":"Ve\u00edculos autom\u00f3veis de passageiros","VL_FOB":4126794468,"hhi_pauta":0.2002748856,"hhi_portuario":0.3386946798}]